burnham/__init__.py
burnham/cli.py
burnham-0.1.0.dev2.dist-info/LICENSE
burnham-0.1.0.dev2.dist-info/METADATA
burnham-0.1.0.dev2.dist-info/WHEEL
burnham-0.1.0.dev2.dist-info/entry_points.txt
burnham-0.1.0.dev2.dist-info/top_level.txt
burnham-0.1.0.dev2.dist-info/RECORD
